youtube_web_api/__init__.py
youtube_web_api/core.py
youtube_web_api/utils.py
youtube_api_web-0.1.2.dist-info/METADATA
youtube_api_web-0.1.2.dist-info/WHEEL
youtube_api_web-0.1.2.dist-info/top_level.txt
youtube_api_web-0.1.2.dist-info/RECORD
